lumi_filter/__init__.py
lumi_filter/backend.py
lumi_filter/field.py
lumi_filter/map.py
lumi_filter/model.py
lumi_filter/operator.py
lumi_filter/shortcut.py
lumi_filter/util.py
lumi_filter-0.2.0.dist-info/METADATA
lumi_filter-0.2.0.dist-info/WHEEL
lumi_filter-0.2.0.dist-info/licenses/LICENSE
lumi_filter-0.2.0.dist-info/RECORD
