Metadata-Version: 2.4
Name: lumi-filter
Version: 0.2.0
Summary: A powerful and flexible data filtering library with unified interface for multiple data sources
Project-URL: Homepage, https://github.com/chaleaoch/lumi_filter
Project-URL: Documentation, https://github.com/chaleaoch/lumi_filter
Project-URL: Repository, https://github.com/chaleaoch/lumi_filter
Project-URL: Bug Tracker, https://github.com/chaleaoch/lumi_filter/issues
Author-email: chaleaoch <chaleaoch@gmail.com>
Maintainer-email: chaleaoch <chaleaoch@gmail.com>
License: MIT
License-File: LICENSE
Keywords: filter,flask,peewee,pydantic
Classifier: Development Status :: 3 - Alpha
Classifier: Intended Audience :: Developers
Classifier: License :: OSI Approved :: MIT License
Classifier: Programming Language :: Python :: 3
Classifier: Programming Language :: Python :: 3.12
Classifier: Topic :: Database
Classifier: Topic :: Software Development :: Libraries :: Python Modules
Requires-Python: >=3.12
Requires-Dist: peewee>=3.18.2
Requires-Dist: pydantic>=2.11.7
